.gitignore
COPYING.LGPLv3
LICENSE
Makefile
NEWS.txt
README.md
conf.py
index.rst
setup.py
openpower/README.txt
openpower/isa.mdwn
openpower/isa/bcd.mdwn
openpower/isa/branch.mdwn
openpower/isa/comparefixed.mdwn
openpower/isa/condition.mdwn
openpower/isa/fixedarith.mdwn
openpower/isa/fixedldstcache.mdwn
openpower/isa/fixedload.mdwn
openpower/isa/fixedlogical.mdwn
openpower/isa/fixedshift.mdwn
openpower/isa/fixedstore.mdwn
openpower/isa/fixedtrap.mdwn
openpower/isa/fparith.mdwn
openpower/isa/fpcvt.mdwn
openpower/isa/fpload.mdwn
openpower/isa/fpmove.mdwn
openpower/isa/fpstore.mdwn
openpower/isa/simplev.mdwn
openpower/isa/sprset.mdwn
openpower/isa/stringldst.mdwn
openpower/isa/system.mdwn
openpower/isafunctions/fpfromint.mdwn
openpower/isatables/LDSTRM-2P-1S1D.csv
openpower/isatables/LDSTRM-2P-1S2D.csv
openpower/isatables/LDSTRM-2P-2S.csv
openpower/isatables/LDSTRM-2P-2S1D.csv
openpower/isatables/LDSTRM-2P-3S.csv
openpower/isatables/RM-1P-2S1D.csv
openpower/isatables/RM-1P-3S1D.csv
openpower/isatables/RM-2P-1S1D.csv
openpower/isatables/RM-2P-2S1D.csv
openpower/isatables/extra.csv
openpower/isatables/fields.text
openpower/isatables/fields.txt
openpower/isatables/major.csv
openpower/isatables/minor_19.csv
openpower/isatables/minor_19_00000.csv
openpower/isatables/minor_19_valid.csv
openpower/isatables/minor_22.csv
openpower/isatables/minor_30.csv
openpower/isatables/minor_31.csv
openpower/isatables/minor_58.csv
openpower/isatables/minor_59.csv
openpower/isatables/minor_62.csv
openpower/isatables/minor_63.csv
openpower/isatables/sprs.csv
src/libresoc_openpower_isa.egg-info/PKG-INFO
src/libresoc_openpower_isa.egg-info/SOURCES.txt
src/libresoc_openpower_isa.egg-info/dependency_links.txt
src/libresoc_openpower_isa.egg-info/entry_points.txt
src/libresoc_openpower_isa.egg-info/not-zip-safe
src/libresoc_openpower_isa.egg-info/requires.txt
src/libresoc_openpower_isa.egg-info/top_level.txt
src/openpower/__init__.py
src/openpower/consts.py
src/openpower/endian.py
src/openpower/exceptions.py
src/openpower/nmigen.py
src/openpower/state.py
src/openpower/util.py
src/openpower/decoder/__init__.py
src/openpower/decoder/decode2execute1.py
src/openpower/decoder/helpers.py
src/openpower/decoder/orderedset.py
src/openpower/decoder/power_decoder.py
src/openpower/decoder/power_decoder2.py
src/openpower/decoder/power_enums.py
