Metadata-Version: 2.1
Name: libresoc-openpower-isa
Version: 0.0.3
Summary: OpenPOWER ISA resources including a python-based simulator
Home-page: http://git.libre-soc.org/?p=openpower-isa.git
Author: Luke Kenneth Casson Leighton
Author-email: lkcl@libre-soc.org
License: LGPLv3+
Keywords: nmigen libre-soc openpower simulator
Platform: UNKNOWN
Classifier: Topic :: Software Development
Classifier: License :: OSI Approved :: GNU Lesser General Public License v3 or later (LGPLv3+)
Classifier: Programming Language :: Python :: 3
Classifier: Operating System :: OS Independent
